lbsnstructure/__init__.py
lbsnstructure/interlinkage_pb2.py
lbsnstructure/py.typed
lbsnstructure/social_pb2.py
lbsnstructure/social_pb2.pyi
lbsnstructure/spatial_pb2.py
lbsnstructure/spatial_pb2.pyi
lbsnstructure/temporal_pb2.py
lbsnstructure/temporal_pb2.pyi
lbsnstructure/topical_pb2.py
lbsnstructure/topical_pb2.pyi
lbsnstructure/version.py
lbsnstructure-1.3.0.dist-info/LICENSE.md
lbsnstructure-1.3.0.dist-info/METADATA
lbsnstructure-1.3.0.dist-info/WHEEL
lbsnstructure-1.3.0.dist-info/top_level.txt
lbsnstructure-1.3.0.dist-info/RECORD
