Metadata-Version: 2.1
Name: lbsnstructure
Version: 1.3.0
Summary: A common language independent and cross-network social-media data scheme.
Author: Filip Krumpe, Marc Löchner
Author-email: Alexander Dunkel <alexander.dunkel@tu-dresden.de>
License: MIT
Project-URL: Homepage, https://lbsn.vgiscience.org/
Requires-Python: >=3.7
License-File: LICENSE.md
Requires-Dist: protobuf
